onnigiri/__init__.py
onnigiri/main.py
onnigiri-0.4.0.dist-info/LICENSE
onnigiri-0.4.0.dist-info/METADATA
onnigiri-0.4.0.dist-info/WHEEL
onnigiri-0.4.0.dist-info/entry_points.txt
onnigiri-0.4.0.dist-info/RECORD
