Metadata-Version: 2.1
Name: onnigiri
Version: 0.4.0
Summary: onnx-divider
Home-page: https://github.com/Idein/onnigiri
License: Apache-2.0
Keywords: onnx
Author: Idein Inc.
Requires-Python: >=3.9,<4.0
Classifier: License :: OSI Approved :: Apache Software License
Classifier: Programming Language :: Python :: 3
Classifier: Programming Language :: Python :: 3.9
Classifier: Programming Language :: Python :: 3.10
Classifier: Programming Language :: Python :: 3.11
Classifier: Programming Language :: Python :: 3.12
Requires-Dist: onnx (>=1.9.0,<2.0.0)
Requires-Dist: onnx-simplifier (>=0.4,<0.5)
Requires-Dist: onnxruntime (>=1.2.0,<2.0.0)
Project-URL: Repository, https://github.com/Idein/onnigiri
